ChangeLog
LICENSE
MANIFEST.in
README.rst
TODO
setup.py
docs/DEPENDENCIES.txt
docs/HISTORY.txt
docs/INSTALL.txt
docs/Makefile
docs/PRELUDE.txt
docs/USAGE.txt
docs/conf.py
docs/index.rst
docs/_build/doctrees/environment.pickle
docs/_build/doctrees/index.doctree
docs/_build/html/.buildinfo
docs/_build/html/genindex.html
docs/_build/html/index.html
docs/_build/html/objects.inv
docs/_build/html/search.html
docs/_build/html/searchindex.js
docs/_build/html/_sources/index.txt
docs/_build/html/_static/ajax-loader.gif
docs/_build/html/_static/alabaster.css
docs/_build/html/_static/basic.css
docs/_build/html/_static/comment-bright.png
docs/_build/html/_static/comment-close.png
docs/_build/html/_static/comment.png
docs/_build/html/_static/doctools.js
docs/_build/html/_static/down-pressed.png
docs/_build/html/_static/down.png
docs/_build/html/_static/file.png
docs/_build/html/_static/jquery-1.11.1.js
docs/_build/html/_static/jquery.js
docs/_build/html/_static/minus.png
docs/_build/html/_static/plus.png
docs/_build/html/_static/pygments.css
docs/_build/html/_static/searchtools.js
docs/_build/html/_static/underscore-1.3.1.js
docs/_build/html/_static/underscore.js
docs/_build/html/_static/up-pressed.png
docs/_build/html/_static/up.png
docs/_build/html/_static/websupport.js
docs/specs/pre-version-1.0.txt
docs/specs/version-1.0.txt
docs/specs/version-2.0-proposed.txt
docs/specs/version-2.0.txt
examples/ssl/cacert.pem
examples/ssl/client.py
examples/ssl/privkey.pem
examples/ssl/server.py
examples/tcp/client.py
examples/tcp/client_subhandled.py
examples/tcp/server.tac
examples/tcp/server_subhandled.tac
examples/web/client.py
examples/web/server.tac
examples/webAuth/client.py
examples/webAuth/passwd.db
examples/webAuth/server.tac
txJSON_RPC.egg-info/PKG-INFO
txJSON_RPC.egg-info/SOURCES.txt
txJSON_RPC.egg-info/dependency_links.txt
txJSON_RPC.egg-info/requires.txt
txJSON_RPC.egg-info/top_level.txt
txjsonrpc/__init__.py
txjsonrpc/auth.py
txjsonrpc/jsonrpc.py
txjsonrpc/jsonrpclib.py
txjsonrpc/__pycache__/__init__.cpython-34.pyc
txjsonrpc/netstring/__init__.py
txjsonrpc/netstring/jsonrpc.py
txjsonrpc/netstring/test/__init__.py
