Metadata-Version: 1.1
Name: txJSON-RPC
Version: 0.5
Summary: Code for creating Twisted JSON-RPC servers and clients.
Home-page: http://github.com/rockstar/txjsonrpc
Author: Paul Hummer
Author-email: paul@eventuallyanyway.com
License: BSD, GPL
Platform: UNKNOWN
Classifier: Development Status :: 4 - Beta
Classifier: Intended Audience :: Developers
Classifier: Programming Language :: Python
